Metadata-Version: 2.1
Name: physicscalc
Version: 0.2
Summary: This is the package that houses various functions which can be used to calculate values for problems involving circuit design , value of the components which are needed to construct the circuit and so on
Home-page: https://github.com/The-SocialLion/physicscalc
Author: ['Vishal Balaji Sivaraman']
Author-email: vb.sivaraman_official@yahoo.com
License: MIT
Download-URL: https://github.com/The-SocialLion/physicscalc/archive/master.zip
Keywords: physics,calculator,physicscalculations,Research,solutions
Platform: UNKNOWN
Classifier: Development Status :: 3 - Alpha
Classifier: Intended Audience :: Developers
Classifier: Topic :: Software Development :: Build Tools
Classifier: License :: OSI Approved :: MIT License
Classifier: Programming Language :: Python :: 3
Classifier: Programming Language :: Python :: 3.4
Classifier: Programming Language :: Python :: 3.5
Classifier: Programming Language :: Python :: 3.6
Classifier: Programming Language :: Python :: 3.7
Classifier: Programming Language :: Python :: 3.8
